gpt_code_ui/__init__.py
gpt_code_ui/main.py
gpt_code_ui/kernel_program/__init__.py
gpt_code_ui/kernel_program/config.py
gpt_code_ui/kernel_program/kernel_manager.py
gpt_code_ui/kernel_program/launch_kernel.py
gpt_code_ui/kernel_program/main.py
gpt_code_ui/kernel_program/utils.py
gpt_code_ui/webapp/__init__.py
gpt_code_ui/webapp/main.py
gpt_code_ui/webapp/static/index.html
gpt_code_ui/webapp/static/assets/assistant.svg
gpt_code_ui/webapp/static/assets/index-085f551a.js
gpt_code_ui/webapp/static/assets/index-0d7e582a.css
gpt_code_ui-0.42.40.dist-info/LICENSE
gpt_code_ui-0.42.40.dist-info/METADATA
gpt_code_ui-0.42.40.dist-info/WHEEL
gpt_code_ui-0.42.40.dist-info/entry_points.txt
gpt_code_ui-0.42.40.dist-info/top_level.txt
gpt_code_ui-0.42.40.dist-info/RECORD
