Metadata-Version: 2.1
Name: gpt-code-ui
Version: 0.42.40
Summary: An Open Source version of ChatGPT Code Interpreter
License-File: LICENSE
Requires-Dist: ipykernel (<7,>=6)
Requires-Dist: snakemq (<2,>=1)
Requires-Dist: requests (<3,>=2)
Requires-Dist: Flask (<3,>=2)
Requires-Dist: flask-cors (<4,>=3)
Requires-Dist: python-dotenv (<2,>=0.18)
Requires-Dist: pandas (<2,>=1.3)
Requires-Dist: openai (<1,>=0.25)
